README.md
setup.py
sicklib.py
sicklib.egg-info/PKG-INFO
sicklib.egg-info/SOURCES.txt
sicklib.egg-info/dependency_links.txt
sicklib.egg-info/requires.txt
sicklib.egg-info/top_level.txt