Metadata-Version: 2.1
Name: sicklib
Version: 0.1.0
Summary: sicklib
Home-page: https://github.com/vesche/sicklib
Author: Austin Jackson
Author-email: vesche@protonmail.com
